./.gitattributes
./.gitignore
./LICENSE
./README.md
./SECURITY.md
./config.json
./configuration_phi3_v.py
./correct_inference.py
./generation_config.json
./image_embedding_phi3_v.py
./image_processing_phi3_v.py
./model.safetensors.index.json
./modeling_phi3_v.py
./preprocessor_config.json
./processing_phi3_v.py
./pyproject.toml
./requirements.txt
./special_tokens_map.json
./tokenizer.json
./tokenizer_config.json
./train.py
./train_lora.py
./.vscode/settings.json
./checkpoints/base/CODE_OF_CONDUCT.md
./checkpoints/base/LICENSE
./checkpoints/base/README.md
./checkpoints/base/SECURITY.md
./checkpoints/base/SUPPORT.md
./checkpoints/base/config.json
./checkpoints/base/configuration_phi3_v.py
./checkpoints/base/correct_inference.py
./checkpoints/base/image_embedding_phi3_v.py
./checkpoints/base/image_processing_phi3_v.py
./checkpoints/base/model.safetensors.index.json
./checkpoints/base/modeling_phi3_v.py
./checkpoints/base/preprocessor_config.json
./checkpoints/base/processing_phi3_v.py
./checkpoints/base/pyproject.toml
./checkpoints/base/requirements.txt
./checkpoints/base/special_tokens_map.json
./checkpoints/base/test.py
./checkpoints/base/tokenizer.json
./checkpoints/base/tokenizer_config.json
./checkpoints/base/train.py
./checkpoints/checkpoint-650/CODE_OF_CONDUCT.md
./checkpoints/checkpoint-650/LICENSE
./checkpoints/checkpoint-650/README.md
./checkpoints/checkpoint-650/SECURITY.md
./checkpoints/checkpoint-650/SUPPORT.md
./checkpoints/checkpoint-650/config.json
./checkpoints/checkpoint-650/configuration_phi3_v.py
./checkpoints/checkpoint-650/correct_inference.py
./checkpoints/checkpoint-650/generation_config.json
./checkpoints/checkpoint-650/image_embedding_phi3_v.py
./checkpoints/checkpoint-650/image_processing_phi3_v.py
./checkpoints/checkpoint-650/modeling_phi3_v.py
./checkpoints/checkpoint-650/preprocessor_config.json
./checkpoints/checkpoint-650/processing_phi3_v.py
./checkpoints/checkpoint-650/pyproject.toml
phi3v_spatial-0.0.1.dist-info/METADATA
phi3v_spatial-0.0.1.dist-info/WHEEL
phi3v_spatial-0.0.1.dist-info/licenses/LICENSE
phi3v_spatial-0.0.1.dist-info/RECORD
