Metadata-Version: 2.3
Name: phi3v_spatial
Version: 0.0.1
Summary: Spatial VLM for 3D Object Detection and Reasoning
Project-URL: Documentation, https://github.com/mbodiai/phi3v-spatial#readme
Project-URL: Issues, https://github.com/mbodiai/phi3v-spatial/issues
Project-URL: Source, https://github.com/mbodiai/phi3v-spatial
Author-email: Mbodi AI Team <hello@mbodi.ai>
License-Expression: Apache-2.0
License-File: LICENSE
Classifier: Development Status :: 4 - Beta
Classifier: Programming Language :: Python
Classifier: Programming Language :: Python :: 3.8
Classifier: Programming Language :: Python :: 3.9
Classifier: Programming Language :: Python :: 3.10
Classifier: Programming Language :: Python :: 3.11
Classifier: Programming Language :: Python :: 3.12
Classifier: Programming Language :: Python :: Implementation :: CPython
Classifier: Programming Language :: Python :: Implementation :: PyPy
Requires-Python: >=3.10
Requires-Dist: datasets
Requires-Dist: gradio
Requires-Dist: pytest
Requires-Dist: torch
Requires-Dist: torchvision
Provides-Extra: all
Requires-Dist: accelerate; extra == 'all'
Requires-Dist: datasets; extra == 'all'
Requires-Dist: gradio; extra == 'all'
Requires-Dist: psutil; extra == 'all'
Requires-Dist: pytest; extra == 'all'
Requires-Dist: torch; extra == 'all'
Requires-Dist: torchvision; extra == 'all'
